business_rule_engine/__init__.py
business_rule_engine/exceptions.py
business_rule_engine-0.2.0.dist-info/LICENSE
business_rule_engine-0.2.0.dist-info/METADATA
business_rule_engine-0.2.0.dist-info/WHEEL
business_rule_engine-0.2.0.dist-info/top_level.txt
business_rule_engine-0.2.0.dist-info/RECORD
