Metadata-Version: 2.1
Name: business-rule-engine
Version: 0.2.0
Summary: Python DSL for setting up business intelligence rules
Home-page: https://github.com/manfred-kaiser/business-rule-engine
Author: Manfred Kaiser
Author-email: manfred.kaiser@logfile.at
License: UNKNOWN
Project-URL: Source, https://github.com/manfred-kaiser/business-rule-engine
Project-URL: Tracker, https://github.com/manfred-kaiser/business-rule-engine/issues
Keywords: business rules engine
Platform: UNKNOWN
Classifier: Programming Language :: Python :: 3
Classifier: Programming Language :: Python :: 3.6
Classifier: Programming Language :: Python :: 3.7
Classifier: Programming Language :: Python :: 3.8
Requires-Python: >= 3.6
License-File: LICENSE
Requires-Dist: formulas
